[
    {
      "name": "任務開始：菸霧下的謎團",
      "act_id": "1",
      "content": "【任務日誌】你是『青春調查局』的新探員，今天接到一項神秘任務：\n在城市的霧氣中，有一種看不見的敵人——「菸」。\n它悄悄地影響著不同性別的生活方式與健康。\n\n局長交給你一份檔案：「近20年來男性吸菸率下降25.6%，但女性卻微幅上升。任務：找出原因！」\n\n你準備好了嗎？",
      "interaction_type": "buttons",
      "interaction_data": {
        "buttons": [
          {
            "text": "接下任務！",
            "interaction_check": "勇敢的探員總是先行一步！任務開始！"
          },
          {
            "text": "再想一下...",
            "interaction_check": "局長皺起眉頭：『年輕人，這世界不會等你準備好！』"
          }
        ]
      },
      "next_do": "2",
      "display_order": "1"
    },
    {
      "name": "線索一：數據的煙霧",
      "act_id": "2",
      "content": "你潛入『健康統計局』的資料庫。螢幕上閃爍著數字：\n男性吸菸率下降25.6%，女性卻上升0.2%。\n女性吸菸者中，自評健康『不好』的比例比不吸菸者高。\n\n副局長低聲說：「如果宣導都一樣，為什麼效果不同？」\n\n你覺得原因可能是——",
      "interaction_type": "buttons",
      "interaction_data": {
        "buttons": [
          {
            "text": "女性受到不同社會壓力",
            "interaction_check": "你注意到，性別角色的期待常讓女性更難拒絕某些社交行為。"
          },
          {
            "text": "宣導沒有針對女性需求",
            "interaction_check": "你記下筆記：『一體適用的政策，有時反而忽略了差異。』"
          },
          {
            "text": "這只是數字誤差",
            "interaction_check": "你輕輕搖頭——但如果是誤差，為什麼持續了二十年？"
          }
        ]
      },
      "next_do": "3",
      "display_order": "2"
    },
    {
      "name": "線索二：生活的裂縫",
      "act_id": "3",
      "content": "你打開第二份資料。女性在『月收入兩萬以下』或『離婚、喪偶、未婚』群體的吸菸率特別高。\n男性也有類似情況，但更集中在『離婚或喪偶』族群。\n\n你發現，這不只是數字，而是生活的壓力。\n如果你是偵探，你會想蒐集哪些資訊來找出真正的原因？",
      "interaction_type": "input",
      "interaction_data": {
        "inputs": [
          {
            "placeholder": "輸入你想調查的項目（例如：心理壓力、孤單感、職場文化...）",
            "interaction_check": "好主意，這些資料或許能揭開隱藏在生活中的性別壓力。"
          }
        ]
      },
      "next_do": "4",
      "display_order": "3"
    },
    {
      "name": "線索三：職場的煙圈",
      "act_id": "4",
      "content": "你走進一間咖啡廳，牆上掛著報導：『女性吸菸率最高的行業：藝術娛樂、資訊傳播、金融保險、餐飲業』。\n隔壁桌有人輕聲說：「這些工作都壓力大啊～」\n\n你觀察到，這些行業有一個共通點是——",
      "interaction_type": "buttons",
      "interaction_data": {
        "buttons": [
          {
            "text": "需要面對人群與社交壓力",
            "interaction_check": "對！有時吸菸被誤認為是『融入群體』的一種社交行為。"
          },
          {
            "text": "長時間工作、精神緊繃",
            "interaction_check": "沒錯，菸變成了短暫的逃避與放鬆方式。"
          },
          {
            "text": "形象與人際關係密切相關",
            "interaction_check": "有趣的觀點——在某些行業中，『拿菸』甚至被視為成熟或酷的象徵。"
          }
        ]
      },
      "next_do": "5",
      "display_order": "4"
    },
    {
      "name": "任務挑戰：重設防菸策略",
      "act_id": "5",
      "content": "局長拍著你的肩膀說：「幹得好，探員！現在由你設計一項新年度防菸計畫，讓政策更有性別觀點。」\n請輸入你的構想，例如：\n- 為餐飲業女性設立『壓力釋放社群』\n- 為單親媽媽提供免費戒菸課程與心理支持\n- 與學校合作，製作性別友善的健康教育動畫",
      "interaction_type": "input",
      "interaction_data": {
        "inputs": [
        {
          "placeholder": "輸入你的創意計畫！",
          "interaction_check": "局長微笑：『不錯，這樣的計畫能讓防菸更貼近人心。』"
        }
        ]
      },
      "next_do": "6",
      "display_order": "5"
    },
    {
      "name": "結局：菸霧散去",
      "act_id": "6",
      "content": "你完成了任務，城市的天空變得更清晰。局長說：『真正的改變，來自看見被忽略的人。』\n\n恭喜你，青春調查局正式授予你——『性別觀點防菸特派員』徽章！\n\n想再挑戰一次不同選項，看看劇情會怎麼變嗎？",
      "interaction_type": "buttons",
      "interaction_data": {
        "buttons": [
          {
            "text": "重新挑戰！",
            "interaction_check": "你重新戴上耳機，準備再潛入數據的世界。"
          },
          {
            "text": "分享我的任務成果",
            "interaction_check": "局長點頭：『讓更多人知道你的發現吧！』"
          }
        ]
      },
      "next_do": "1",
      "display_order": "6"
    }
  ]
  